<?xml version="1.0" encoding="UTF-8"?>
<objects serializationModel="Studio.02.00.00">
	<object class="AudioFile" id="{b6559b96-6a26-4f1e-8d4a-c82acb5a82ff}">
		<property name="assetPath">
			<value>PlayerJumpShort.wav</value>
		</property>
		<property name="frequencyInKHz">
			<value>44.0999985</value>
		</property>
		<property name="channelCount">
			<value>2</value>
		</property>
		<property name="length">
			<value>0.13707482993197279</value>
		</property>
		<relationship name="masterAssetFolder">
			<destination>{dca8ee79-cd13-4391-8bf5-7b9d6d229d05}</destination>
		</relationship>
	</object>
</objects>
